VGA/rtl/top.v
module vga_generator #(
	parameter H_RES = 640,	// Do phan giai ngang
	parameter V_RES = 480,	// Do phan giai doc
	parameter H_FP = 16,	// Front porch ngang
	parameter H_SYNC = 96,	// Sync pulse ngang
	parameter H_BP = 48,	// Back porch ngang
	parameter V_FP = 10,	// Front porch doc
	parameter V_SYNC = 2,	// Sync pulse doc
	parameter V_BP = 33	// Back porch doc
)(
	input wire clk,		// Tin hieu xung clock
	input wire rst_n,	// Tin hieu reset (active low)
	output reg hsync,	// Tin hieu dong bo ngang
	output reg vsync,	// Tin hieu dong bo doc
	output reg [10:0] pixel_x,	// Vi tri pixel ngang
	output reg [9:0] pixel_y,	// Vi tri pixel doc
	output reg video_active,	// Tin hieu hien thi hop le
	output reg [7:0] rgb_r,		// Thanh phan mau do,
	output reg [7:0] rgb_g,		// Thanh phan mau xanh la
	output reg [7:0] rgb_b		// Thanh phan mau xanh duong
);

// Tong so pixel ngang va doc
localparam H_TOTAL = H_RES + H_FP + H_SYNC + H_BP;
localparam V_TOTAL = V_RES + V_FP + V_SYNC + V_BP;

// Bo dem pixel
reg [10:0] h_counter;	// Bo dem ngang
reg [9:0] v_counter;	// Bo dem doc.

// Dem pixel va dong
always @(posedge clk or negedge rst_n) begin
	if(!rst_n) begin
		h_counter <= 11'h000;
		v_counter <= 10'h000;
	end else begin
		if(h_counter == H_TOTAL - 1'b1) begin
			h_counter <= 11'h000;
			if(v_counter == V_TOTAL - 1'b1) begin
				v_counter <= 10'h000;
			end else begin
				v_counter <= v_counter + 1'b1;
			end
		end else begin
			h_counter <= h_counter + 1'b1;
		end
	end
end

// Tao tin hieu hsync va vsync 
always @(posedge clk or negedge rst_n) begin
	if(!rst_n) begin
		hsync <= 1'b1;
		vsync <= 1'b1;
	end else begin
		hsync <= (h_counter >= H_RES + H_FP && h_counter < H_RES + H_FP + H_SYNC) ? 1'b0 : 1'b1;
		vsync <= (v_counter >= V_RES + V_FP && v_counter < V_RES + V_FP + V_SYNC) ? 1'b0 : 1'b1;
	end
end

// Xac dinh vung dia chi
always @(posedge clk or negedge rst_n) begin
	if(!rst_n) begin
		video_active <= 1'b0;
		pixel_x <= 11'h000;
		pixel_y <= 10'h000;
	end else begin
		video_active <= (h_counter < H_RES) && (v_counter < V_RES);
		pixel_x <= (video_active) ? h_counter : 1'b0;
		pixel_y <= (video_active) ? v_counter : 1'b0;
	end
end

// Tao tin hieu RGB
always @(posedge clk or negedge rst_n) begin
	if(!rst_n) begin
		rgb_r <= 8'h00;
		rgb_g <= 8'h00;
		rgb_b <= 8'h00;
	end else if (video_active) begin
		// Hien thi gradien mau theo vi tri pixel
		rgb_r <= pixel_x[7:0];	// mau do theo toa do x
		rgb_g <= pixel_y[7:0];	// mau xanh theo toa do y
		rgb_b <= pixel_x[7:0] + pixel_y[7:0];   // mau xanh la tong hop toa do x va y
	end else begin
		rgb_r <= 8'h00;
		rgb_g <= 8'h00;
		rgb_b <= 8'h00;
	end
end

endmodule

VGA/tb/test_bench.v
`timescale 1ns/1ps
module test_bench;
	parameter H_RES = 640;
	parameter V_RES = 480;
	parameter H_FP = 16;
	parameter H_SYNC = 96;
	parameter H_BP = 48;
	parameter V_FP = 10;
	parameter V_SYNC = 2;
	parameter V_BP = 33;

	parameter CLK_PERIOD = 10;	//100mhz clock

	reg clk;
	reg rst_n;
	wire hsync;
	wire vsync;
	wire [10:0] pixel_x;
	wire [9:0] pixel_y;
	wire video_active;
	wire [7:0] rgb_r;
	wire [7:0] rgb_g;
	wire [7:0] rgb_b;

	// Instance of DUT
	vga_generator #(
		.H_RES(H_RES),
		.V_RES(V_RES),
		.H_FP(H_FP),
		.H_SYNC(H_SYNC),
		.H_BP(H_BP),
		.V_FP(V_FP),
		.V_SYNC(V_SYNC),
		.V_BP(V_BP)
	) dut (
		.clk(clk),
		.rst_n(rst_n),
		.hsync(hsync),
		.vsync(vsync),
		.pixel_x(pixel_x),
		.pixel_y(pixel_y),
		.video_active(video_active),
		.rgb_r(rgb_r),
		.rgb_g(rgb_g),
		.rgb_b(rgb_b)
	);

	localparam H_TOTAL = H_RES + H_FP + H_SYNC + H_BP;
	localparam V_TOTAL = V_RES + V_FP + V_SYNC + V_BP;

	initial begin
		clk = 0;
		forever #(CLK_PERIOD/2) clk = ~clk;
	end
	
	task verify;
		input exp_hsync;
		input exp_vsync;
		input [10:0] exp_pixel_x;
		input [9:0] exp_pixel_y;
		input exp_video_active;
		input [7:0] exp_rgb_r;
		input [7:0] exp_rgb_g;
		input [7:0] exp_rgb_b;
		begin
			$display("At time: %t", $time);
			if(hsync == exp_hsync && vsync == exp_vsync && pixel_x == exp_pixel_x && pixel_y == exp_pixel_y && rgb_r == exp_rgb_r && rgb_g == exp_rgb_g && rgb_b == exp_rgb_b) begin
			     $display("-----------------------------------TESTCASE PASSED-------------------------------------------------------");
			     $display("Expected hsync: 1'b%b, Got hsync: 1'b%b, Expected vsync: 1'b%b, Got vsync: 1'b%b",exp_hsync, hsync, exp_vsync, vsync);
			     $display("Expected pixel x: 11'h%h, Got pixel x: 11'h%h, Expected pixel y: 10'h%h, Got pixel y: 10'h%h", exp_pixel_x, pixel_x, exp_pixel_y, pixel_y);
			     $display("Expected rgb_r: 8'h%h, Got rgb_r: 8'h%h, Expected rgb_g: 8'h%h, Got rgb_g: 8'h%h, Expected rgb_b: 8'h%h, Got rgb_b: 8'h%h", exp_rgb_r, rgb_r, exp_rgb_g, rgb_g, exp_rgb_b, rgb_b);
			     $display("---------------------------------------------------------------------------------------------------------");
		     end else begin
			     $display("-----------------------------------TESTCASE FAILED-------------------------------------------------------");
			     $display("Expected hsync: 1'b%b, Got hsync: 1'b%b, Expected vsync: 1'b%b, Got vsync: 1'b%b",exp_hsync, hsync, exp_vsync, vsync);
			     $display("Expected pixel x: 11'h%h, Got pixel x: 11'h%h, Expected pixel y: 10'h%h, Got pixel y: 10'h%h", exp_pixel_x, pixel_x, exp_pixel_y, pixel_y);
			     $display("Expected rgb_r: 8'h%h, Got rgb_r: 8'h%h, Expected rgb_g: 8'h%h, Got rgb_g: 8'h%h, Expected rgb_b: 8'h%h, Got rgb_b: 8'h%h", exp_rgb_r, rgb_r, exp_rgb_g, rgb_g, exp_rgb_b, rgb_b);
			     $display("---------------------------------------------------------------------------------------------------------");
		     end
	     end
     endtask

	initial begin
		$dumpfile("test_bench.vcd");
		$dumpvars(0, test_bench);

		$display("-----------------------------------------------------------------------------------------------------------------------------------------");
		$display("---------------------------------- TESTBENCH FOR VGA SIGNAL GENERATOR -------------------------------------------------------------------");
		$display("-----------------------------------------------------------------------------------------------------------------------------------------");

		rst_n = 0;
		@(posedge clk);
		verify(1'b1, 1'b1,11'h000, 10'h000, 1'b0,8'h00, 8'h00, 8'h00);

		rst_n = 1;
		@(posedge clk);
		verify(1'b1, 1'b1,11'h000, 10'h000, 1'b0,8'h00, 8'h00, 8'h00);

		repeat(H_RES + H_FP) @(posedge clk);
		verify(1'b0, 1'b1,11'h000, 10'h000, 1'b0,8'h00, 8'h00, 8'h00);
		
		repeat(H_TOTAL - H_RES - H_FP) @(posedge clk);
		verify(1'b1, 1'b1,11'h000, 10'h000, 1'b1,8'h00, 8'h00, 8'h00);
		
		repeat(50) @(posedge clk);
		verify(1'b1, 1'b1,11'd50, 10'h001, 1'b1,8'd49, 8'h01, 8'd50);
		
		repeat(600) @(posedge clk);
		verify(1'b1, 1'b1, 11'h000, 10'h000, 1'b0, 8'h00, 8'h00, 8'h00);
		
		repeat(6) @(posedge clk);
		verify(1'b0, 1'b1,11'h000, 10'h000, 1'b0, 8'h00, 8'h00, 8'h00);
		
		rst_n = 0;
		@(posedge clk);

		rst_n = 1;
		repeat(V_RES) @(posedge clk);
		verify(1'b1, 1'b1, V_RES - 1, 10'h000, 1'b1,V_RES - 2, 8'h00, V_RES - 2);

		#100;
		$finish;

	end
endmodule

VGA/sim/test_bench.vcd
$date
	Thu Jan 23 22:21:35 2025
$end
$version
	Icarus Verilog
$end
$timescale
	1ps
$end
$scope module test_bench $end
$var wire 1 ! vsync $end
$var wire 1 " video_active $end
$var wire 8 # rgb_r [7:0] $end
$var wire 8 $ rgb_g [7:0] $end
$var wire 8 % rgb_b [7:0] $end
$var wire 10 & pixel_y [9:0] $end
$var wire 11 ' pixel_x [10:0] $end
$var wire 1 ( hsync $end
$var parameter 32 ) CLK_PERIOD $end
$var parameter 32 * H_BP $end
$var parameter 32 + H_FP $end
$var parameter 32 , H_RES $end
$var parameter 32 - H_SYNC $end
$var parameter 35 . H_TOTAL $end
$var parameter 32 / V_BP $end
$var parameter 32 0 V_FP $end
$var parameter 32 1 V_RES $end
$var parameter 32 2 V_SYNC $end
$var parameter 35 3 V_TOTAL $end
$var reg 1 4 clk $end
$var reg 1 5 rst_n $end
$scope module dut $end
$var wire 1 4 clk $end
$var wire 1 5 rst_n $end
$var parameter 32 6 H_BP $end
$var parameter 32 7 H_FP $end
$var parameter 32 8 H_RES $end
$var parameter 32 9 H_SYNC $end
$var parameter 35 : H_TOTAL $end
$var parameter 32 ; V_BP $end
$var parameter 32 < V_FP $end
$var parameter 32 = V_RES $end
$var parameter 32 > V_SYNC $end
$var parameter 35 ? V_TOTAL $end
$var reg 11 @ h_counter [10:0] $end
$var reg 1 ( hsync $end
$var reg 11 A pixel_x [10:0] $end
$var reg 10 B pixel_y [9:0] $end
$var reg 8 C rgb_b [7:0] $end
$var reg 8 D rgb_g [7:0] $end
$var reg 8 E rgb_r [7:0] $end
$var reg 10 F v_counter [9:0] $end
$var reg 1 " video_active $end
$var reg 1 ! vsync $end
$upscope $end
$scope task verify $end
$var reg 1 G exp_hsync $end
$var reg 11 H exp_pixel_x [10:0] $end
$var reg 10 I exp_pixel_y [9:0] $end
$var reg 8 J exp_rgb_b [7:0] $end
$var reg 8 K exp_rgb_g [7:0] $end
$var reg 8 L exp_rgb_r [7:0] $end
$var reg 1 M exp_video_active $end
$var reg 1 N exp_vsync $end
$upscope $end
$upscope $end
$enddefinitions $end
$comment Show the parameter values. $end
$dumpall
b1000001101 ?
b10 >
b111100000 =
b1010 <
b100001 ;
b1100100000 :
b1100000 9
b1010000000 8
b10000 7
b110000 6
b1000001101 3
b10 2
b111100000 1
b1010 0
b100001 /
b1100100000 .
b1100000 -
b1010000000 ,
b10000 +
b110000 *
b1010 )
$end
#0
$dumpvars
xN
xM
bx L
bx K
bx J
bx I
bx H
xG
b0 F
b0 E
b0 D
b0 C
b0 B
b0 A
b0 @
05
04
1(
b0 '
b0 &
b0 %
b0 $
b0 #
0"
1!
$end
#5000
1"
b1 @
15
b0 J
b0 K
b0 L
0M
b0 I
b0 H
1N
1G
14
#10000
04
#15000
b10 @
b1 '
b1 A
14
#20000
04
#25000
b1 %
b1 C
b1 #
b1 E
b10 '
b10 A
b11 @
14
#30000
04
#35000
b100 @
b11 '
b11 A
b10 %
b10 C
b10 #
b10 E
14
#40000
04
#45000
b11 %
b11 C
b11 #
b11 E
b100 '
b100 A
b101 @
14
#50000
04
#55000
b110 @
b101 '
b101 A
b100 %
b100 C
b100 #
b100 E
14
#60000
04
#65000
b101 %
b101 C
b101 #
b101 E
b110 '
b110 A
b111 @
14
#70000
04
#75000
b1000 @
b111 '
b111 A
b110 %
b110 C
b110 #
b110 E
14
#80000
04
#85000
b111 %
b111 C
b111 #
b111 E
b1000 '
b1000 A
b1001 @
14
#90000
04
#95000
b1010 @
b1001 '
b1001 A
b1000 %
b1000 C
b1000 #
b1000 E
14
#100000
04
#105000
b1001 %
b1001 C
b1001 #
b1001 E
b1010 '
b1010 A
b1011 @
14
#110000
04
#115000
b1100 @
b1011 '
b1011 A
b1010 %
b1010 C
b1010 #
b1010 E
14
#120000
04
#125000
b1011 %
b1011 C
b1011 #
b1011 E
b1100 '
b1100 A
b1101 @
14
#130000
04
#135000
b1110 @
b1101 '
b1101 A
b1100 %
b1100 C
b1100 #
b1100 E
14
#140000
04
#145000
b1101 %
b1101 C
b1101 #
b1101 E
b1110 '
b1110 A
b1111 @
14
#150000
04
#155000
b10000 @
b1111 '
b1111 A
b1110 %
b1110 C
b1110 #
b1110 E
14
#160000
04
#165000
b1111 %
b1111 C
b1111 #
b1111 E
b10000 '
b10000 A
b10001 @
14
#170000
04
#175000
b10010 @
b10001 '
b10001 A
b10000 %
b10000 C
b10000 #
b10000 E
14
#180000
04
#185000
b10001 %
b10001 C
b10001 #
b10001 E
b10010 '
b10010 A
b10011 @
14
#190000
04
#195000
b10100 @
b10011 '
b10011 A
b10010 %
b10010 C
b10010 #
b10010 E
14
#200000
04
#205000
b10011 %
b10011 C
b10011 #
b10011 E
b10100 '
b10100 A
b10101 @
14
#210000
04
#215000
b10110 @
b10101 '
b10101 A
b10100 %
b10100 C
b10100 #
b10100 E
14
#220000
04
#225000
b10101 %
b10101 C
b10101 #
b10101 E
b10110 '
b10110 A
b10111 @
14
#230000
04
#235000
b11000 @
b10111 '
b10111 A
b10110 %
b10110 C
b10110 #
b10110 E
14
#240000
04
#245000
b10111 %
b10111 C
b10111 #
b10111 E
b11000 '
b11000 A
b11001 @
14
#250000
04
#255000
b11010 @
b11001 '
b11001 A
b11000 %
b11000 C
b11000 #
b11000 E
14
#260000
04
#265000
b11001 %
b11001 C
b11001 #
b11001 E
b11010 '
b11010 A
b11011 @
14
#270000
04
#275000
b11100 @
b11011 '
b11011 A
b11010 %
b11010 C
b11010 #
b11010 E
14
#280000
04
#285000
b11011 %
b11011 C
b11011 #
b11011 E
b11100 '
b11100 A
b11101 @
14
#290000
04
#295000
b11110 @
b11101 '
b11101 A
b11100 %
b11100 C
b11100 #
b11100 E
14
#300000
04
#305000
b11101 %
b11101 C
b11101 #
b11101 E
b11110 '
b11110 A
b11111 @
14
#310000
04
#315000
b100000 @
b11111 '
b11111 A
b11110 %
b11110 C
b11110 #
b11110 E
14
#320000
04
#325000
b11111 %
b11111 C
b11111 #
b11111 E
b100000 '
b100000 A
b100001 @
14
#330000
04
#335000
b100010 @
b100001 '
b100001 A
b100000 %
b100000 C
b100000 #
b100000 E
14
#340000
04
#345000
b100001 %
b100001 C
b100001 #
b100001 E
b100010 '
b100010 A
b100011 @
14
#350000
04
#355000
b100100 @
b100011 '
b100011 A
b100010 %
b100010 C
b100010 #
b100010 E
14
#360000
04
#365000
b100011 %
b100011 C
b100011 #
b100011 E
b100100 '
b100100 A
b100101 @
14
#370000
04
#375000
b100110 @
b100101 '
b100101 A
b100100 %
b100100 C
b100100 #
b100100 E
14
#380000
04
#385000
b100101 %
b100101 C
b100101 #
b100101 E
b100110 '
b100110 A
b100111 @
14
#390000
04
#395000
b101000 @
b100111 '
b100111 A
b100110 %
b100110 C
b100110 #
b100110 E
14
#400000
04
#405000
b100111 %
b100111 C
b100111 #
b100111 E
b101000 '
b101000 A
b101001 @
14
#410000
04
#415000
b101010 @
b101001 '
b101001 A
b101000 %
b101000 C
b101000 #
b101000 E
14
#420000
04
#425000
b101001 %
b101001 C
b101001 #
b101001 E
b101010 '
b101010 A
b101011 @
14
#430000
04
#435000
b101100 @
b101011 '
b101011 A
b101010 %
b101010 C
b101010 #
b101010 E
14
#440000
04
#445000
b101011 %
b101011 C
b101011 #
b101011 E
b101100 '
b101100 A
b101101 @
14
#450000
04
#455000
b101110 @
b101101 '
b101101 A
b101100 %
b101100 C
b101100 #
b101100 E
14
#460000
04
#465000
b101101 %
b101101 C
b101101 #
b101101 E
b101110 '
b101110 A
b101111 @
14
#470000
04
#475000
b110000 @
b101111 '
b101111 A
b101110 %
b101110 C
b101110 #
b101110 E
14
#480000
04
#485000
b101111 %
b101111 C
b101111 #
b101111 E
b110000 '
b110000 A
b110001 @
14
#490000
04
#495000
b110010 @
b110001 '
b110001 A
b110000 %
b110000 C
b110000 #
b110000 E
14
#500000
04
#505000
b110001 %
b110001 C
b110001 #
b110001 E
b110010 '
b110010 A
b110011 @
14
#510000
04
#515000
b110100 @
b110011 '
b110011 A
b110010 %
b110010 C
b110010 #
b110010 E
14
#520000
04
#525000
b110011 %
b110011 C
b110011 #
b110011 E
b110100 '
b110100 A
b110101 @
14
#530000
04
#535000
b110110 @
b110101 '
b110101 A
b110100 %
b110100 C
b110100 #
b110100 E
14
#540000
04
#545000
b110101 %
b110101 C
b110101 #
b110101 E
b110110 '
b110110 A
b110111 @
14
#550000
04
#555000
b111000 @
b110111 '
b110111 A
b110110 %
b110110 C
b110110 #
b110110 E
14
#560000
04
#565000
b110111 %
b110111 C
b110111 #
b110111 E
b111000 '
b111000 A
b111001 @
14
#570000
04
#575000
b111010 @
b111001 '
b111001 A
b111000 %
b111000 C
b111000 #
b111000 E
14
#580000
04
#585000
b111001 %
b111001 C
b111001 #
b111001 E
b111010 '
b111010 A
b111011 @
14
#590000
04
#595000
b111100 @
b111011 '
b111011 A
b111010 %
b111010 C
b111010 #
b111010 E
14
#600000
04
#605000
b111011 %
b111011 C
b111011 #
b111011 E
b111100 '
b111100 A
b111101 @
14
#610000
04
#615000
b111110 @
b111101 '
b111101 A
b111100 %
b111100 C
b111100 #
b111100 E
14
#620000
04
#625000
b111101 %
b111101 C
b111101 #
b111101 E
b111110 '
b111110 A
b111111 @
14
#630000
04
#635000
b1000000 @
b111111 '
b111111 A
b111110 %
b111110 C
b111110 #
b111110 E
14
#640000
04
#645000
b111111 %
b111111 C
b111111 #
b111111 E
b1000000 '
b1000000 A
b1000001 @
14
#650000
04
#655000
b1000010 @
b1000001 '
b1000001 A
b1000000 %
b1000000 C
b1000000 #
b1000000 E
14
#660000
04
#665000
b1000001 %
b1000001 C
b1000001 #
b1000001 E
b1000010 '
b1000010 A
b1000011 @
14
#670000
04
#675000
b1000100 @
b1000011 '
b1000011 A
b1000010 %
b1000010 C
b1000010 #
b1000010 E
14
#680000
04
#685000
b1000011 %
b1000011 C
b1000011 #
b1000011 E
b1000100 '
b1000100 A
b1000101 @
14
#690000
04
#695000
b1000110 @
b1000101 '
b1000101 A
b1000100 %
b1000100 C
b1000100 #
b1000100 E
14
#700000
04
#705000
b1000101 %
b1000101 C
b1000101 #
b1000101 E
b1000110 '
b1000110 A
b1000111 @
14
#710000
04
#715000
b1001000 @
b1000111 '
b1000111 A
b1000110 %
b1000110 C
b1000110 #
b1000110 E
14
#720000
04
#725000
b1000111 %
b1000111 C
b1000111 #
b1000111 E
b1001000 '
b1001000 A
b1001001 @
14
#730000
04
#735000
b1001010 @
b1001001 '
b1001001 A
b1001000 %
b1001000 C
b1001000 #
b1001000 E
14
#740000
04
#745000
b1001001 %
b1001001 C
b1001001 #
b1001001 E
b1001010 '
b1001010 A
b1001011 @
14
#750000
04
#755000
b1001100 @
b1001011 '
b1001011 A
b1001010 %
b1001010 C
b1001010 #
b1001010 E
14
#760000
04
#765000
b1001011 %
b1001011 C
b1001011 #
b1001011 E
b1001100 '
b1001100 A
b1001101 @
14
#770000
04
#775000
b1001110 @
b1001101 '
b1001101 A
b1001100 %
b1001100 C
b1001100 #
b1001100 E
14
#780000
04
#785000
b1001101 %
b1001101 C
b1001101 #
b1001101 E
b1001110 '
b1001110 A
b1001111 @
14
#790000
04
#795000
b1010000 @
b1001111 '
b1001111 A
b1001110 %
b1001110 C
b1001110 #
b1001110 E
14
#800000
04
#805000
b1001111 %
b1001111 C
b1001111 #
b1001111 E
b1010000 '
b1010000 A
b1010001 @
14
#810000
04
#815000
b1010010 @
b1010001 '
b1010001 A
b1010000 %
b1010000 C
b1010000 #
b1010000 E
14
#820000
04
#825000
b1010001 %
b1010001 C
b1010001 #
b1010001 E
b1010010 '
b1010010 A
b1010011 @
14
#830000
04
#835000
b1010100 @
b1010011 '
b1010011 A
b1010010 %
b1010010 C
b1010010 #
b1010010 E
14
#840000
04
#845000
b1010011 %
b1010011 C
b1010011 #
b1010011 E
b1010100 '
b1010100 A
b1010101 @
14
#850000
04
#855000
b1010110 @
b1010101 '
b1010101 A
b1010100 %
b1010100 C
b1010100 #
b1010100 E
14
#860000
04
#865000
b1010101 %
b1010101 C
b1010101 #
b1010101 E
b1010110 '
b1010110 A
b1010111 @
14
#870000
04
#875000
b1011000 @
b1010111 '
b1010111 A
b1010110 %
b1010110 C
b1010110 #
b1010110 E
14
#880000
04
#885000
b1010111 %
b1010111 C
b1010111 #
b1010111 E
b1011000 '
b1011000 A
b1011001 @
14
#890000
04
#895000
b1011010 @
b1011001 '
b1011001 A
b1011000 %
b1011000 C
b1011000 #
b1011000 E
14
#900000
04
#905000
b1011001 %
b1011001 C
b1011001 #
b1011001 E
b1011010 '
b1011010 A
b1011011 @
14
#910000
04
#915000
b1011100 @
b1011011 '
b1011011 A
b1011010 %
b1011010 C
b1011010 #
b1011010 E
14
#920000
04
#925000
b1011011 %
b1011011 C
b1011011 #
b1011011 E
b1011100 '
b1011100 A
b1011101 @
14
#930000
04
#935000
b1011110 @
b1011101 '
b1011101 A
b1011100 %
b1011100 C
b1011100 #
b1011100 E
14
#940000
04
#945000
b1011101 %
b1011101 C
b1011101 #
b1011101 E
b1011110 '
b1011110 A
b1011111 @
14
#950000
04
#955000
b1100000 @
b1011111 '
b1011111 A
b1011110 %
b1011110 C
b1011110 #
b1011110 E
14
#960000
04
#965000
b1011111 %
b1011111 C
b1011111 #
b1011111 E
b1100000 '
b1100000 A
b1100001 @
14
#970000
04
#975000
b1100010 @
b1100001 '
b1100001 A
b1100000 %
b1100000 C
b1100000 #
b1100000 E
14
#980000
04
#985000
b1100001 %
b1100001 C
b1100001 #
b1100001 E
b1100010 '
b1100010 A
b1100011 @
14
#990000
04
#995000
b1100100 @
b1100011 '
b1100011 A
b1100010 %
b1100010 C
b1100010 #
b1100010 E
14
#1000000
04
#1005000
b1100011 %
b1100011 C
b1100011 #
b1100011 E
b1100100 '
b1100100 A
b1100101 @
14
#1010000
04
#1015000
b1100110 @
b1100101 '
b1100101 A
b1100100 %
b1100100 C
b1100100 #
b1100100 E
14
#1020000
04
#1025000
b1100101 %
b1100101 C
b1100101 #
b1100101 E
b1100110 '
b1100110 A
b1100111 @
14
#1030000
04
#1035000
b1101000 @
b1100111 '
b1100111 A
b1100110 %
b1100110 C
b1100110 #
b1100110 E
14
#1040000
04
#1045000
b1100111 %
b1100111 C
b1100111 #
b1100111 E
b1101000 '
b1101000 A
b1101001 @
14
#1050000
04
#1055000
b1101010 @
b1101001 '
b1101001 A
b1101000 %
b1101000 C
b1101000 #
b1101000 E
14
#1060000
04
#1065000
b1101001 %
b1101001 C
b1101001 #
b1101001 E
b1101010 '
b1101010 A
b1101011 @
14
#1070000
04
#1075000
b1101100 @
b1101011 '
b1101011 A
b1101010 %
b1101010 C
b1101010 #
b1101010 E
14
#1080000
04
#1085000
b1101011 %
b1101011 C
b1101011 #
b1101011 E
b1101100 '
b1101100 A
b1101101 @
14
#1090000
04
#1095000
b1101110 @
b1101101 '
b1101101 A
b1101100 %
b1101100 C
b1101100 #
b1101100 E
14
#1100000
04
#1105000
b1101101 %
b1101101 C
b1101101 #
b1101101 E
b1101110 '
b1101110 A
b1101111 @
14
#1110000
04
#1115000
b1110000 @
b1101111 '
b1101111 A
b1101110 %
b1101110 C
b1101110 #
b1101110 E
14
#1120000
04
#1125000
b1101111 %
b1101111 C
b1101111 #
b1101111 E
b1110000 '
b1110000 A
b1110001 @
14
#1130000
04
#1135000
b1110010 @
b1110001 '
b1110001 A
b1110000 %
b1110000 C
b1110000 #
b1110000 E
14
#1140000
04
#1145000
b1110001 %
b1110001 C
b1110001 #
b1110001 E
b1110010 '
b1110010 A
b1110011 @
14
#1150000
04
#1155000
b1110100 @
b1110011 '
b1110011 A
b1110010 %
b1110010 C
b1110010 #
b1110010 E
14
#1160000
04
#1165000
b1110011 %
b1110011 C
b1110011 #
b1110011 E
b1110100 '
b1110100 A
b1110101 @
14
#1170000
04
#1175000
b1110110 @
b1110101 '
b1110101 A
b1110100 %
b1110100 C
b1110100 #
b1110100 E
14
#1180000
04
#1185000
b1110101 %
b1110101 C
b1110101 #
b1110101 E
b1110110 '
b1110110 A
b1110111 @
14
#1190000
04
#1195000
b1111000 @
b1110111 '
b1110111 A
b1110110 %
b1110110 C
b1110110 #
b1110110 E
14
#1200000
04
#1205000
b1110111 %
b1110111 C
b1110111 #
b1110111 E
b1111000 '
b1111000 A
b1111001 @
14
#1210000
04
#1215000
b1111010 @
b1111001 '
b1111001 A
b1111000 %
b1111000 C
b1111000 #
b1111000 E
14
#1220000
04
#1225000
b1111001 %
b1111001 C
b1111001 #
b1111001 E
b1111010 '
b1111010 A
b1111011 @
14
#1230000
04
#1235000
b1111100 @
b1111011 '
b1111011 A
b1111010 %
b1111010 C
b1111010 #
b1111010 E
14
#1240000
04
#1245000
b1111011 %
b1111011 C
b1111011 #
b1111011 E
b1111100 '
b1111100 A
b1111101 @
14
#1250000
04
#1255000
b1111110 @
b1111101 '
b1111101 A
b1111100 %
b1111100 C
b1111100 #
b1111100 E
14
#1260000
04
#1265000
b1111101 %
b1111101 C
b1111101 #
b1111101 E
b1111110 '
b1111110 A
b1111111 @
14
#1270000
04
#1275000
b10000000 @
b1111111 '
b1111111 A
b1111110 %
b1111110 C
b1111110 #
b1111110 E
14
#1280000
04
#1285000
b1111111 %
b1111111 C
b1111111 #
b1111111 E
b10000000 '
b10000000 A
b10000001 @
14
#1290000
04
#1295000
b10000010 @
b10000001 '
b10000001 A
b10000000 %
b10000000 C
b10000000 #
b10000000 E
14
#1300000
04
#1305000
b10000001 %
b10000001 C
b10000001 #
b10000001 E
b10000010 '
b10000010 A
b10000011 @
14
#1310000
04
#1315000
b10000100 @
b10000011 '
b10000011 A
b10000010 %
b10000010 C
b10000010 #
b10000010 E
14
#1320000
04
#1325000
b10000011 %
b10000011 C
b10000011 #
b10000011 E
b10000100 '
b10000100 A
b10000101 @
14
#1330000
04
#1335000
b10000110 @
b10000101 '
b10000101 A
b10000100 %
b10000100 C
b10000100 #
b10000100 E
14
#1340000
04
#1345000
b10000101 %
b10000101 C
b10000101 #
b10000101 E
b10000110 '
b10000110 A
b10000111 @
14
#1350000
04
#1355000
b10001000 @
b10000111 '
b10000111 A
b10000110 %
b10000110 C
b10000110 #
b10000110 E
14
#1360000
04
#1365000
b10000111 %
b10000111 C
b10000111 #
b10000111 E
b10001000 '
b10001000 A
b10001001 @
14
#1370000
04
#1375000
b10001010 @
b10001001 '
b10001001 A
b10001000 %
b10001000 C
b10001000 #
b10001000 E
14
#1380000
04
#1385000
b10001001 %
b10001001 C
b10001001 #
b10001001 E
b10001010 '
b10001010 A
b10001011 @
14
#1390000
04
#1395000
b10001100 @
b10001011 '
b10001011 A
b10001010 %
b10001010 C
b10001010 #
b10001010 E
14
#1400000
04
#1405000
b10001011 %
b10001011 C
b10001011 #
b10001011 E
b10001100 '
b10001100 A
b10001101 @
14
#1410000
04
#1415000
b10001110 @
b10001101 '
b10001101 A
b10001100 %
b10001100 C
b10001100 #
b10001100 E
14
#1420000
04
#1425000
b10001101 %
b10001101 C
b10001101 #
b10001101 E
b10001110 '
b10001110 A
b10001111 @
14
#1430000
04
#1435000
b10010000 @
b10001111 '
b10001111 A
b10001110 %
b10001110 C
b10001110 #
b10001110 E
14
#1440000
04
#1445000
b10001111 %
b10001111 C
b10001111 #
b10001111 E
b10010000 '
b10010000 A
b10010001 @
14
#1450000
04
#1455000
b10010010 @
b10010001 '
b10010001 A
b10010000 %
b10010000 C
b10010000 #
b10010000 E
14
#1460000
04
#1465000
b10010001 %
b10010001 C
b10010001 #
b10010001 E
b10010010 '
b10010010 A
b10010011 @
14
#1470000
04
#1475000
b10010100 @
b10010011 '
b10010011 A
b10010010 %
b10010010 C
b10010010 #
b10010010 E
14
#1480000
04
#1485000
b10010011 %
b10010011 C
b10010011 #
b10010011 E
b10010100 '
b10010100 A
b10010101 @
14
#1490000
04
#1495000
b10010110 @
b10010101 '
b10010101 A
b10010100 %
b10010100 C
b10010100 #
b10010100 E
14
#1500000
04
#1505000
b10010101 %
b10010101 C
b10010101 #
b10010101 E
b10010110 '
b10010110 A
b10010111 @
14
#1510000
04
#1515000
b10011000 @
b10010111 '
b10010111 A
b10010110 %
b10010110 C
b10010110 #
b10010110 E
14
#1520000
04
#1525000
b10010111 %
b10010111 C
b10010111 #
b10010111 E
b10011000 '
b10011000 A
b10011001 @
14
#1530000
04
#1535000
b10011010 @
b10011001 '
b10011001 A
b10011000 %
b10011000 C
b10011000 #
b10011000 E
14
#1540000
04
#1545000
b10011001 %
b10011001 C
b10011001 #
b10011001 E
b10011010 '
b10011010 A
b10011011 @
14
#1550000
04
#1555000
b10011100 @
b10011011 '
b10011011 A
b10011010 %
b10011010 C
b10011010 #
b10011010 E
14
#1560000
04
#1565000
b10011011 %
b10011011 C
b10011011 #
b10011011 E
b10011100 '
b10011100 A
b10011101 @
14
#1570000
04
#1575000
b10011110 @
b10011101 '
b10011101 A
b10011100 %
b10011100 C
b10011100 #
b10011100 E
14
#1580000
04
#1585000
b10011101 %
b10011101 C
b10011101 #
b10011101 E
b10011110 '
b10011110 A
b10011111 @
14
#1590000
04
#1595000
b10100000 @
b10011111 '
b10011111 A
b10011110 %
b10011110 C
b10011110 #
b10011110 E
14
#1600000
04
#1605000
b10011111 %
b10011111 C
b10011111 #
b10011111 E
b10100000 '
b10100000 A
b10100001 @
14
#1610000
04
#1615000
b10100010 @
b10100001 '
b10100001 A
b10100000 %
b10100000 C
b10100000 #
b10100000 E
14
#1620000
04
#1625000
b10100001 %
b10100001 C
b10100001 #
b10100001 E
b10100010 '
b10100010 A
b10100011 @
14
#1630000
04
#1635000
b10100100 @
b10100011 '
b10100011 A
b10100010 %
b10100010 C
b10100010 #
b10100010 E
14
#1640000
04
